jsondesign/__init__.py
jsondesign/entity.py
jsondesign/schema_store.py
jsondesign/utils.py
jsondesign-0.2.0.dist-info/LICENSE
jsondesign-0.2.0.dist-info/METADATA
jsondesign-0.2.0.dist-info/WHEEL
jsondesign-0.2.0.dist-info/top_level.txt
jsondesign-0.2.0.dist-info/RECORD
