Metadata-Version: 2.1
Name: jsondesign
Version: 0.2.0
Summary: A Python 3 library handling JSON schema for mimicking entities design in an OO-fashion
Home-page: https://github.com/lasircc/jsondesign
Author: LAS Team
Author-email: las@ircc.it
License: MIT
Platform: UNKNOWN
Classifier: License :: OSI Approved :: MIT License
Classifier: Programming Language :: Python :: 3.6
Classifier: Programming Language :: Python :: 3.7
Requires-Dist: attrs (==19.1.0)
Requires-Dist: jsonref (==0.2)
Requires-Dist: jsonschema (==3.0.2)
Requires-Dist: pyrsistent (==0.15.4)
Requires-Dist: six (==1.12.0)
